polyshell-0.1.0.dist-info/METADATA
polyshell-0.1.0.dist-info/WHEEL
polyshell-0.1.0.dist-info/entry_points.txt
polyshell-0.1.0.dist-info/licenses/LICENSE
polyshell/__init__.py
polyshell/_cli.py
polyshell/_polyshell.cpython-310-aarch64-linux-gnu.so
polyshell/_polyshell.pyi
polyshell/py.typed
polyshell-0.1.0.dist-info/RECORD
